classutils/__init__.py
classutils/_metadata.py
classutils/introspection.py
classutils/observer.py
classutils/profiling.py
classutils/queue_processor.py
classutils/singleton.py
classutils/thread_pool.py
classutils/decorators/__init__.py
classutils/decorators/deprecation_warning.py
classutils/decorators/in_class_result_caching.py
classutils/decorators/profiling.py
classutils/unittests/__init__.py
classutils/unittests/test_in_class_result_cache.py
classutils/unittests/test_observer.py
classutils/unittests/test_singleton.py
classutils-1.18.2.dist-info/LICENSE.txt
classutils-1.18.2.dist-info/METADATA
classutils-1.18.2.dist-info/WHEEL
classutils-1.18.2.dist-info/entry_points.txt
classutils-1.18.2.dist-info/top_level.txt
classutils-1.18.2.dist-info/RECORD
