Metadata-Version: 2.1
Name: classutils
Version: 1.18.2
Summary: A collection of utilites to enhance Python classes.
Home-page: https://bitbucket.org/daycoder/classutils.git
Author: Hywel Thomas
Author-email: hywel.thomas@mac.com
License: MIT
Download-URL: https://bitbucket.org/daycoder/classutils.git/get/1.18.2.tar
Keywords: Class,Observer
Platform: UNKNOWN
Classifier: Development Status :: 3 - Alpha
Classifier: Intended Audience :: Developers
Classifier: License :: OSI Approved :: MIT License
Classifier: Programming Language :: Python :: 2
Classifier: Programming Language :: Python :: 2.7
Classifier: Programming Language :: Python :: 3
Classifier: Programming Language :: Python :: 3.6
Classifier: Topic :: Utilities
License-File: LICENSE.txt
Requires-Dist: future (>=0.16.0)
Requires-Dist: fdutil (>=1.6.2)
Requires-Dist: timingsutil (>=1.5.0)
Requires-Dist: requests (>=2.7.0)
Requires-Dist: tableutil (>=2.2.4)
Provides-Extra: test
